branches/__init__.py
branches/branch_ops.py
git_hooks/__init__.py
git_hooks/git_hook.py
git_hooks/files/__init__.py
git_hooks/files/pre-commit.py
git_hooks/files/pre-push.py
git_tools/__init__.py
git_tools/config_utils.py
git_tools/cookie_util.py
git_tools/git_env.py
git_tools/git_home_page.py
git_tools/git_list_task.py
git_tools/git_pick_task.py
git_tools/git_push_tag.py
git_tools/gitlab_apis.py
git_tools/gitrepo.py
git_tools/job_dto.py
git_tools/job_info.py
git_tools/sorted_key_utils.py
git_tools/sqlite_util.py
git_tools/table_column.py
git_tools/test_git_repo.py
git_tools/test_pipeline_info.py
git_tools/test_third_jar.py
git_tools/toggle_util.py
git_tools/config/git-project-config.json
smart_gitlab-1.1.8.dist-info/METADATA
smart_gitlab-1.1.8.dist-info/WHEEL
smart_gitlab-1.1.8.dist-info/entry_points.txt
smart_gitlab-1.1.8.dist-info/top_level.txt
smart_gitlab-1.1.8.dist-info/RECORD
